zissou/VERSION
zissou/__init__.py
zissou/cli/__init__.py
zissou-0.0.0.dist-info/entry_points.txt
zissou-0.0.0.dist-info/LICENSE-APACHE
zissou-0.0.0.dist-info/LICENSE-MIT
zissou-0.0.0.dist-info/WHEEL
zissou-0.0.0.dist-info/METADATA
zissou-0.0.0.dist-info/RECORD
