Metadata-Version: 2.1
Name: zissou
Version: 0.0.0
Summary: Python library and tools for Zissou.
Home-page: https://github.com/nickray/zissou
License: UNKNOWN
Author: Nicolas Stalder
Author-email: n@stalder.io
Requires-Python: >=3.6
Classifier: License :: OSI Approved :: MIT License
Classifier: License :: OSI Approved :: Apache Software License
Classifier: Intended Audience :: Developers
Classifier: Intended Audience :: End Users/Desktop
Classifier: Programming Language :: Python :: 3 :: Only
Classifier: Programming Language :: Python :: 3.6
Classifier: Programming Language :: Python :: 3.7
Requires-Dist: click >= 7.0
Requires-Dist: pyserial
Requires-Dist: pyusb
